violetSpider/README.md
violetSpider/__init__.py
violetSpider/core/__init__.py
violetSpider/core/error.py
violetSpider/core/model.py
violetSpider-1.1.3.data/data/README.md
violetSpider-1.1.3.dist-info/METADATA
violetSpider-1.1.3.dist-info/WHEEL
violetSpider-1.1.3.dist-info/top_level.txt
violetSpider-1.1.3.dist-info/RECORD
