Metadata-Version: 2.1
Name: violetSpider
Version: 1.1.3
Summary: 新冠疫情数据爬取
Author: violet-drowning
Author-email: 459427688@qq.com
Platform: any
Requires-Dist: requests
